the_segmentation_game/__init__.py
the_segmentation_game/_dock_widget.py
the_segmentation_game/metrics.py
the_segmentation_game/_tests/__init__.py
the_segmentation_game/_tests/test_dock_widget.py
the_segmentation_game/_tests/test_metrics.py
the_segmentation_game-0.2.0.dist-info/LICENSE
the_segmentation_game-0.2.0.dist-info/METADATA
the_segmentation_game-0.2.0.dist-info/WHEEL
the_segmentation_game-0.2.0.dist-info/entry_points.txt
the_segmentation_game-0.2.0.dist-info/top_level.txt
the_segmentation_game-0.2.0.dist-info/RECORD
